MANIFEST.in
README.md
setup.py
web/favicon.ico
web/index.html
web/server.py
web/assets/fonts/B612.ttf
web/assets/fonts/Cutive.ttf
web/assets/fonts/Fira.ttf
web/assets/fonts/IBMPlex.ttf
web/assets/fonts/Major.ttf
web/assets/fonts/Nanum.ttf
web/assets/fonts/Nova.ttf
web/assets/fonts/ShareTech.ttf
web/assets/fonts/VT323.ttf
web/assets/images/dhlab-mark.svg
web/assets/images/heightmap.jpg
web/assets/images/preview.png
web/assets/js/dat.gui.min.js
web/assets/js/stats.min.js
web/assets/js/three.min.js
web/assets/js/trackball-controls.min.js
web/assets/js/tweenlite.min.js
web/assets/js/wordmap.js
web/data/manifest.json
web/data/texts.json
web/data/layouts/img/img_file-yale.png-n_clusters-7.json
web/data/layouts/obj/obj_file-castle.obj-n_clusters-7.json
web/data/layouts/obj/obj_file-elephant.obj-n_clusters-7.json
web/data/layouts/obj/obj_file-ivysaur.obj-n_clusters-7.json
web/data/layouts/obj/obj_file-mug.obj-n_clusters-7.json
web/data/layouts/tsne/tsne_n_clusters-7-perplexity-10.json
web/data/layouts/tsne/tsne_n_clusters-7-perplexity-2.json
web/data/layouts/tsne/tsne_n_clusters-7-perplexity-20.json
web/data/layouts/tsne/tsne_n_clusters-7-perplexity-5.json
web/data/layouts/tsne/tsne_n_clusters-7-perplexity-[30].json
web/data/layouts/umap/umap_min_dist-0.001-n_clusters-7-n_neighbors-10.json
web/data/layouts/umap/umap_min_dist-0.001-n_clusters-7-n_neighbors-2.json
web/data/layouts/umap/umap_min_dist-0.001-n_clusters-7-n_neighbors-20.json
web/data/layouts/umap/umap_min_dist-0.001-n_clusters-7-n_neighbors-5.json
web/data/layouts/umap/umap_min_dist-0.01-n_clusters-7-n_neighbors-10.json
web/data/layouts/umap/umap_min_dist-0.01-n_clusters-7-n_neighbors-2.json
web/data/layouts/umap/umap_min_dist-0.01-n_clusters-7-n_neighbors-20.json
web/data/layouts/umap/umap_min_dist-0.01-n_clusters-7-n_neighbors-5.json
web/data/layouts/umap/umap_min_dist-0.1-n_clusters-7-n_neighbors-10.json
web/data/layouts/umap/umap_min_dist-0.1-n_clusters-7-n_neighbors-2.json
wordmap.egg-info/PKG-INFO
wordmap.egg-info/SOURCES.txt
wordmap.egg-info/dependency_links.txt
wordmap.egg-info/entry_points.txt
wordmap.egg-info/requires.txt
wordmap.egg-info/top_level.txt
