Metadata-Version: 1.0
Name: wordmap
Version: 0.1.2
Summary: Visualize massive word collections
Home-page: https://github.com/yaledhlab/wordmap
Author: Douglas Duhaime
Author-email: douglas.duhaime@gmail.com
License: MIT
Keywords: webgl,three.js,word2vec,tsne,umap,machine-learning
Platform: UNKNOWN
